coreason_vault/__init__.py
coreason_vault/auth.py
coreason_vault/cipher.py
coreason_vault/config.py
coreason_vault/exceptions.py
coreason_vault/keeper.py
coreason_vault/manager.py
coreason_vault/utils/__init__.py
coreason_vault/utils/logger.py
coreason_vault-0.2.0.dist-info/METADATA
coreason_vault-0.2.0.dist-info/WHEEL
coreason_vault-0.2.0.dist-info/licenses/LICENSE
coreason_vault-0.2.0.dist-info/licenses/NOTICE
coreason_vault-0.2.0.dist-info/RECORD
