Metadata-Version: 2.4
Name: coreason_vault
Version: 0.2.0
Summary: A new Python project.
License: # The Prosperity Public License 3.0.0
License-File: LICENSE
License-File: NOTICE
Author: Gowtham A Rao
Author-email: gowtham.rao@coreason.ai
Requires-Python: >=3.11
Classifier: License :: Other/Proprietary License
Classifier: Programming Language :: Python :: 3.12
Classifier: Operating System :: OS Independent
Requires-Dist: cachetools (>=6.2.4,<7.0.0)
Requires-Dist: hvac (>=2.4.0,<3.0.0)
Requires-Dist: loguru (>=0.7.2,<0.8.0)
Requires-Dist: pydantic (>=2.12.5,<3.0.0)
Requires-Dist: pydantic-settings (>=2.12.0,<3.0.0)
Requires-Dist: requests (>=2.32.5,<3.0.0)
Requires-Dist: tenacity (>=9.1.2,<10.0.0)
Project-URL: Documentation, https://github.com/CoReason-AI/coreason_vault
Project-URL: Homepage, https://github.com/CoReason-AI/coreason_vault
Project-URL: Repository, https://github.com/CoReason-AI/coreason_vault
